{"destination": "AHMEDABAD", "trip_duration": 5, "activities": ["Sightseeing", "Shopping", "Dining", "Museums"], "itinerary": {"destination": "AHMEDABAD", "daily_activities": [[{"activity": "Sightseeing", "location": "Sabarmati Ashram"}, {"activity": "Dining", "location": "Agashiye"}, {"activity": "Shopping", "location": "Law Garden"}], [{"activity": "Museums", "location": "Calico Museum of Textiles"}, {"activity": "Sightseeing", "location": "Bhadra Fort"}, {"activity": "Dining", "location": "The Square"}], [{"activity": "Shopping", "location": "Lal Darwaza"}, {"activity": "Sightseeing", "location": "Sidi Saiyyed Mosque"}, {"activity": "Museums", "location": "Gandhi Smarak Sangrahalaya"}], [{"activity": "Dining", "location": "Vishalla"}, {"activity": "Sightseeing", "location": "Adalaj Vav"}, {"activity": "Shopping", "location": "Manek Chowk"}], [{"activity": "Museums", "location": "Lalbhai Dalpatbhai Museum"}, {"activity": "Sightseeing", "location": "Akshardham Temple"}, {"activity": "Dining", "location": "Swati Snacks"}]]}, "travel_instructions": {"mode_of_transportation": "None", "estimated_travel_time": "0 hours", "estimated_distance": "0 kilometers", "route_details": "Since the starting and ending points are the same (Ahmedabad), no travel is required."}, "coordinates": [23.0215374, 72.5800568], "coordinates1": [23.0145531, 72.5635432], "images": ["https://encrypted-tbn0.gstatic.com/images?q=tbn:ANd9GcQF6EOoEvvzVCxuP1sIl594DnaoLJVvJxO9xQc6jZHzNf5kDySaxks63Aa1p30&s", "https://encrypted-tbn0.gstatic.com/images?q=tbn:ANd9GcRoYv2GBid978thMUiDtGciRfUjBVNKMY0pAjpX5QAbTUjRp2I493kMcePCXA&s", "https://encrypted-tbn0.gstatic.com/images?q=tbn:ANd9GcRY_AyS7UsBUprcVN2yMv1Xbnd-P_zhuV2dVB-z4JYeqtBvVr279ekphfxGFzw&s", "https://encrypted-tbn0.gstatic.com/images?q=tbn:ANd9GcRFBahTVrnHErI_-f_BaBzepRG5PMtnLW1qO4dtAL_E9E_KyC9kmuFXOOm_vbU&s", "https://encrypted-tbn0.gstatic.com/images?q=tbn:ANd9GcRbBLCH_YYNIEomtM92UkXbBzFeKU2xmbKcLfd96-CBgV6tPFMPKvWbDxVNHdA&s", "https://encrypted-tbn0.gstatic.com/images?q=tbn:ANd9GcRXWuU2ox4lm2JypEGW6-WTwFMQOfDm7EJUaFahXCjEDgjfsWLGDC4iKsXWeNM&s"], "generated_at": "2025-01-23T13:35:12.608641"}